{
  "id": "td14",
  "td_num": 14,
  "category": "4",
  "category_title": "관리 노동·역할·완료 기준",
  "title": "시간·관심을 일·취미·외부에 더 배분",
  "format": "adult",
  "why_pool": [
    [
      "다른 일이 반복해서 먼저 오면 현정님은 관계 안에서 자신의 자리가 뒤로 밀린 듯 느낄 수 있어요. 모든 시간을 원하는 것이 아니라 구체적인 연결 시간이 필요했을 가능성이 있어요.",
      "일이나 개인 시간이 필요하다는 것을 알아도, 함께하기로 한 시간이 자꾸 밀리면 현정님 마음에는 소외감이 쌓였을 수 있어요. 관계가 남는 시간에만 놓인 듯 느껴졌을 수 있어요.",
      "휴식이나 개인 활동이 반복해서 우선될 때 현정님은 자신이 덜 중요하게 여겨지는지 확인하고 싶어졌을 수 있어요. 짧더라도 집중해서 함께하는 신호가 필요했을 수 있어요."
    ],
    [
      "‘나는 항상 나중이야’라는 말이 이안이에게는 개인 시간을 모두 문제 삼는 말처럼 닿았을 수 있어요. 그래서 관계 요청보다 자유를 빼앗기는 느낌이 먼저 올라왔을 가능성이 있어요.",
      "휴대폰이나 개인 활동을 지적하는 말이 강하게 들리면 이안이는 쉬는 시간까지 인정받지 못한다고 느꼈을 수 있어요. 그 느낌이 연결보다 방어를 먼저 만들었을 수 있어요.",
      "가족보다 일이 먼저라는 말은 이안이에게 노력이나 피로가 보이지 않는다는 신호처럼 닿았을 수 있어요. 그래서 관계 시간을 정하자는 뜻보다 비난이 먼저 남았을 가능성이 있어요."
    ],
    [
      "이안이는 밀어내려는 마음보다 해야 할 일이나 회복 시간이 필요했던 상태였을 수 있어요. 다만 그 시간이 반복되며 현정님에게 소외감으로 닿는다는 점은 잘 보이지 않았을 수 있어요.",
      "개인 시간이 필요하다는 마음이 커질수록 이안이는 관계 시간을 따로 정해야 한다는 부담을 늦게 느꼈을 수 있어요. 쉬는 것과 연결 신호를 함께 두는 기준이 필요했을 수 있어요.",
      "이안이는 지금 당장 길게 반응하기 어렵다고 느꼈지만, 그것이 관계를 뒤로 미루는 신호로 보일 수 있다는 점은 놓쳤을 수 있어요. 짧은 연결 시간이 다리 역할을 할 수 있었을 수 있어요."
    ],
    [
      "모든 시간을 맞추려 하기보다 짧게 집중할 시간을 정하면 부담이 낮아질 수 있어요. 몇 분이라도 따로 둔 시간이 있으면 밀려난 느낌이 줄어들 가능성이 있어요. 짧은 약속이 관계의 기준이 될 수 있어요.",
      "개인 시간과 관계 시간을 둘 다 보이게 정하면 한쪽이 지워지는 느낌을 줄일 수 있어요. 언제 함께하고 언제 회복할지 기준이 있으면 서로 덜 추측하게 될 수 있어요.",
      "지금 바로 길게 어렵다면 오늘 가능한 짧은 시간을 말해두는 것이 도움이 될 수 있어요. 작은 연결 신호가 있으면 현정님도 기다림을 덜 외롭게 느꼈을 수 있어요. 가능한 시간이 보이는 것이 중요했을 수 있어요."
    ]
  ],
  "a3_pool": [
    {
      "why": "현정님이 원하는 것은 이안이의 모든 시간을 차지하는 것이 아니라, 자신과의 관계도 일정 안에 실제 자리가 있다는 확인일 수 있어요. 연결 시간이 계속 밀리면 처음의 기다림이 서운함과 외로움으로 층층이 쌓일 수 있어요.",
      "src": "td14-say_initiator + ABC·애착 + 정서조절"
    },
    {
      "why": "이안이에게 일이나 취미 시간은 현정님을 피하려는 시간이 아니라, 복잡한 마음과 피로를 낮추는 회복 시간일 수 있어요. 다만 그 필요가 설명되지 않은 채 관계 시간이 계속 뒤로 밀리면 현정님에게는 자신이 우선순위에서 사라진 것처럼 느껴질 수 있어요.",
      "src": "td14-child_explain / td14-translate_pairs + 정서조절 + ABC·애착"
    },
    {
      "why": "“나중에”는 말하는 사람에게는 연결 의사가 있다는 뜻일 수 있지만, 기다리는 사람에게는 끝을 알 수 없는 미룸이 될 수 있어요. 구체적인 시간이 없으면 현정님의 불안이 확인과 재촉으로 커지고, 이안이는 그 재촉을 다시 압박으로 느낄 수 있어요.",
      "src": "td14-say_initiator / td14-say_together + ABC·애착 + 정서조절"
    },
    {
      "why": "이 표현은 개인 시간을 빼앗으려는 것이 아니라 관계의 자리를 확인하고 싶다는 필요를 분명히 해줘요. 이안이는 통제받는다는 방어를 낮추고, 현정님이 실제로 원하는 것이 무엇인지 들을 수 있어요.",
      "src": "td14-say_initiator + ABC·애착 + RSD"
    },
    {
      "why": "개인 시간과 관계 시간을 경쟁시키면 한쪽을 선택할 때마다 다른 한쪽이 거절된 것처럼 느껴질 수 있어요. 두 시간을 따로 정하면 이안이의 회복 필요와 현정님의 연결 필요를 함께 지킬 수 있어요.",
      "src": "td14-say_together + 공동조절 + ABC·애착"
    },
    {
      "why": "이런 표현은 시간 배분의 갈등을 사랑의 크기나 사람의 이기심에 대한 판정으로 바꿔버려요. 반대로 소외감을 과하다고 줄이면 현정님의 실제 외로움이 지워져요. 두 사람의 필요를 인정하면서 시간 구조를 조정해야 해요.",
      "src": "td14-avoid + RSD + ABC·애착"
    },
    {
      "why": "관계 시간을 막연히 기다리지 않고 작게 예약하면 현정님은 언제 연결될지 알 수 있고, 이안이는 개인 시간을 침해받는다는 불안을 덜 수 있어요. 변경할 때 대체 시간을 함께 제시하면 약속이 사라진 것이 아니라 이동한 것이라는 안전 신호가 돼요.",
      "src": "td14-parent_coaching.coaching_steps + 실행기능 스캐폴딩 + 공동조절"
    }
  ],
  "sections": {
    "situation_info": {
      "header": "1. 상황 기본 정보",
      "text": "**상황 이름**: 시간, 에너지, 관심, 실행 자원이 일, 취미, 디지털 활동, 외부 관계, 개인 과제에 반복적으로 더 많이 배분되는 상황 [출처: td14-title]\n\n**핵심 장면**: 한 사람은 일이나 개인 시간, 디지털 활동, 휴식이 필요하다고 느끼고, 다른 한 사람은 관계 시간이 계속 뒤로 밀려 자신이 소외되는 것처럼 느끼는 장면 [출처: td14-say_initiator / td14-say_responder / td14-child_feelings]\n\n**핵심 메커니즘 후보**: 실제 업무 과부하, 번아웃 또는 피로, 개인 회복 시간 필요, 디지털 활동의 즉각 보상, 취미나 개인 활동을 통한 정서 조절, 관계 대화에 대한 회피 [출처: td14-child_explain]"
    },
    "A": {
      "header": "2. A. 개인 결과 [엄마용]",
      "subsections": {
        "A-1. 받아주기": {
          "header": "A-1. 받아주기",
          "text": "현정님, 이안이가 일, 취미, 휴대폰, 디지털 활동, 개인 과제에 반복적으로 더 많은 시간을 쓰고, 함께하기로 한 시간이 계속 밀리면 현정님은 뒤로 밀린 느낌을 받을 수 있어요. [출처: td14-title / td14-say_initiator]\n\n현정님이 원하는 것은 이안이의 모든 시간을 갖겠다는 뜻이 아니라, 관계가 중요하다는 것을 알 수 있는 구체적인 시간과 연결 신호일 수 있습니다. [출처: td14-say_initiator]\n\n다만 이안이 쪽에서는 \"잠깐 쉬는 것까지 문제 삼는 것 같다\", \"내 개인 시간은 인정받지 못한다\"고 느낄 수 있어요. [출처: td14-child_feelings]\n\n오늘의 핵심은 개인 시간과 관계 시간 중 하나만 선택하는 것이 아니라, 둘을 서로 지우지 않도록 따로 정하는 것입니다. [출처: td14-say_together]"
        },
        "A-2. 핵심 이해 4블록": {
          "header": "A-2. 핵심 이해 4블록",
          "tables": [
            {
              "header": [
                "블록",
                "결과문",
                "출처"
              ],
              "rows": [
                {
                  "블록": "현정님의 마음",
                  "결과문": "현정님은 이안이가 일부러 밀어낸다고 단정하려는 것은 아니지만, 반복적으로 다른 일이 먼저 오면 관계 안에서 뒤로 밀린 느낌을 받았을 수 있어요.",
                  "출처": "td14-say_initiator"
                },
                {
                  "블록": "그 말이 이안이에게 닿은 방식",
                  "결과문": "\"너한테 나는 항상 나중이야\", \"휴대폰이 나보다 중요하지?\"처럼 들리면, 이안이는 자신의 휴식이나 개인 시간이 통제받는다고 느낄 수 있어요.",
                  "출처": "td14-avoid / td14-child_feelings"
                },
                {
                  "블록": "이안이의 마음",
                  "결과문": "이안이는 해야 할 일이 많거나, 잠깐 쉬고 싶었거나, 개인 시간이 인정받지 못한다고 느꼈을 수 있어요.",
                  "출처": "td14-child_feelings / td14-child_explain"
                },
                {
                  "블록": "오늘 할 수 있는 것 하나",
                  "결과문": "오늘은 \"나중에\"라고만 하지 않고, 가능한 시간을 함께 말하거나 바쁜 날에도 최소 연결 신호를 정해볼 수 있어요.",
                  "출처": "td14-say_together / td14-parent_coaching.coaching_steps"
                }
              ]
            }
          ]
        },
        "A-3. 깊은 근거": {
          "header": "A-3. 깊은 근거",
          "tables": [
            {
              "header": [
                "항목",
                "내용",
                "출처"
              ],
              "rows": [
                {
                  "항목": "발화 속뜻·닿는 방식",
                  "내용": "현정님의 \"또 나중이야?\"라는 마음 안에는 통제하려는 의도보다, 관계 안에서 소속되어 있다는 신호가 필요하다는 마음이 있을 수 있어요.",
                  "출처": "td14-say_initiator"
                },
                {
                  "항목": "개인 시간과 소외감의 충돌",
                  "내용": "이안이에게는 실제 업무 과부하, 피로, 개인 회복 시간 필요, 디지털 활동의 즉각 보상, 취미를 통한 정서 조절이 있었을 수 있어요.",
                  "출처": "td14-child_explain / td14-translate_pairs"
                },
                {
                  "항목": "\"나중에\"의 문제",
                  "내용": "\"나중에\"라는 말만 반복되면 기다리는 사람은 언제 다시 연결될지 알 수 없어 불확실성이 커질 수 있어요.",
                  "출처": "td14-say_initiator / td14-say_together"
                },
                {
                  "항목": "추천 표현",
                  "내용": "\"내가 원하는 건 네 모든 시간을 갖겠다는 게 아니야. 우리 관계가 중요하다는 것을 알 수 있는 구체적인 시간이 필요해.\"",
                  "출처": "td14-say_initiator"
                },
                {
                  "항목": "함께 쓸 표현",
                  "내용": "\"개인 시간과 관계 시간을 서로 지우지 않도록 따로 정하자.\"",
                  "출처": "td14-say_together"
                },
                {
                  "항목": "피할 표현",
                  "내용": "\"너한테 나는 항상 나중이야\", \"휴대폰이 나보다 중요하지?\", \"너는 가족보다 일이 먼저야\", \"너는 이기적이야\", \"왜 내 시간까지 통제하려고 해?\", \"그 정도로 소외감을 느끼는 건 과해\" 같은 표현은 피해야 해요.",
                  "출처": "td14-avoid"
                },
                {
                  "항목": "오늘의 한 걸음",
                  "내용": "관계 시간을 작고 구체적으로 예약하고, 취소나 변경이 필요할 때는 대체 시간을 함께 제안해볼 수 있어요.",
                  "출처": "td14-parent_coaching.coaching_steps"
                }
              ]
            }
          ]
        }
      }
    },
    "B": {
      "header": "3. B. 개인 결과 [엄마용] — 아빠 정민님 개입 시 조건부 블록",
      "text": "이 칸은 자산에 해당 내용이 없어 비워둡니다. [출처: 자산 없음]"
    },
    "B2_dad": {
      "layer1": "정민님, 누군가의 시간과 관심이 일, 휴대폰, 취미, 개인 시간 쪽으로 반복해서 향하는 장면을 보셨다면, 관계 시간이 뒤로 밀리는 느낌을 받으셨을 수 있어요. \"지금 당장 오래 이야기하자는 게 아닌데, 잠깐의 연결도 어려운 건가?\"라는 서운함이 올라왔을 수도 있어요. 반대로 정민님이 개인 시간이나 휴식이 필요했던 쪽이라면, 관계를 피하려는 것이 아니라 정말 쉬거나 처리해야 할 일이 많았을 수 있어요. 이 장면은 개인 시간과 관계 시간을 서로 지우지 않도록, 가능한 시간을 구체적으로 말하는 쪽으로 볼 수 있어요.",
      "layer2": "**정민님 마음**: 정민님은 관계 시간이 반복해서 뒤로 밀리면, 가족 안에서 자신이나 누군가가 기다리는 사람처럼 남는다고 느끼셨을 수 있어요. **그 행동이 이안이·현정님에게 닿은 방식**: 정민님이 \"나중에\"라고만 하셨다면, 상대에게는 기다림이 끝나지 않는 느낌으로 닿았을 수 있어요. 반대로 정민님이 연결을 요구하셨다면, 상대에게는 개인 시간이 인정받지 못하는 느낌으로 닿았을 수 있어요. **이안이 또는 현정님 마음**: 그 사람은 해야 할 일이 많거나, 잠깐 쉬는 것까지 문제 삼는 것처럼 느꼈을 수 있어요. **오늘 할 수 있는 것 하나**: 정민님은 \"나중에\" 대신 \"오늘 9시에 15분은 집중해서 이야기할게\"처럼 가능한 시간을 구체적으로 말해볼 수 있어요.",
      "layer3": "**발화 속뜻**: \"너한테 나는 항상 나중이야\"라는 말 뒤에는 관계 안에서 뒤로 밀린 느낌과 구체적인 연결 시간이 필요하다는 마음이 있었을 수 있어요. **추천 표현**: \"내가 원하는 건 네 모든 시간을 갖겠다는 게 아니야. 우리 관계가 중요하다는 것을 알 수 있는 구체적인 시간이 필요해.\" **함께 쓸 표현**: \"내 개인 시간이 필요한 것과, 네가 소외감을 느끼지 않도록 연결 신호를 주는 것은 둘 다 중요하다고 생각해.\" **피할 표현**: \"너는 가족보다 일이 먼저야\", \"왜 내 시간까지 통제하려고 해?\"처럼 사랑이나 통제의 문제로 몰아가는 말은 피하는 게 좋아요."
    },
    "C": {
      "header": "4. C. 통합 리포트 [부모 전용]",
      "tables": [
        {
          "header": [
            "블록",
            "내용",
            "출처"
          ],
          "rows": [
            {
              "블록": "1. 우리가 함께 겪은 순간",
              "내용": "오늘은 시간, 에너지, 관심, 실행 자원이 일, 취미, 디지털 활동, 외부 관계, 개인 과제에 반복적으로 더 많이 배분되고, 관계 시간이 뒤로 밀리는 장면이 있었을 수 있어요.",
              "출처": "td14-title"
            },
            {
              "블록": "2. 그때 우리는",
              "내용": "현정님은 관계 안에서 뒤로 밀린 느낌을 받았고, 이안이는 해야 할 일이 많거나 쉬고 싶은 마음, 개인 시간이 필요하다는 마음이 있었을 수 있어요.",
              "출처": "td14-say_initiator / td14-child_feelings"
            },
            {
              "블록": "3. 우리가 다르게 느꼈던 건",
              "내용": "현정님에게는 소외감이나 우선순위에서 밀린 느낌이었고, 이안이에게는 개인 시간과 자유가 통제받는 느낌이었을 수 있어요.",
              "출처": "td14-translate_pairs / td14-child_feelings"
            },
            {
              "블록": "4. 이 순환을 이해하는 열쇠",
              "내용": "이 장면은 사랑의 증명 싸움이 아니라, 시간과 관심 배분의 조정 문제로 다루는 것이 안전합니다.",
              "출처": "td14-say_together"
            },
            {
              "블록": "5. 이렇게 말해보면",
              "내용": "\"일이나 개인 시간이 필요한 건 이해해. 다만 우리 시간도 계속 미뤄지지 않는 기준이 있었으면 해.\"",
              "출처": "td14-say_initiator"
            },
            {
              "블록": "6. 이렇게 해보면",
              "내용": "개인 시간과 관계 시간을 따로 정하고, \"나중에\"라고 말할 때는 가능한 시간을 함께 말해볼 수 있어요.",
              "출처": "td14-say_together / td14-parent_coaching.coaching_steps"
            },
            {
              "블록": "7. 그리고, 현정님께",
              "내용": "소외감이 \"나를 먼저 선택해야 한다\"는 증명 요구로 커지기 전에, 필요한 연결의 종류와 시간을 구체적으로 말하는 것이 좋습니다.",
              "출처": "td14-say_initiator / td14-say_together / td14-parent_coaching.effect_signals"
            }
          ]
        }
      ]
    },
    "D": {
      "tier1": {
        "header": "D-구간1(5~7세). 아이용 결과 리포트 [부모가 읽어주는 3줄 대본]",
        "text": "OO이에게 이렇게 들려주세요: 쉬고 싶어서 속상했지.\nOO이에게 이렇게 들려주세요: 몸이 많이 피곤했던 거야.\nOO이에게 이렇게 들려주세요: 물 한 모금 마시자."
      },
      "tier2": {
        "header": "5. D. 아이용 결과 리포트 [이안이용]",
        "text": "> ✅ **D블록 2인칭 통일 규칙 적용 확인**: 전체 \"너는/네가\"로 일관 유지됨.\n> ✅ **회고 질문 정확도 확인**: 카테고리 4 직접 추출본 기준 — 7개 전부 정확, 교정 사항 없음.",
        "tables": [
          {
            "header": [
              "블록",
              "내용",
              "출처"
            ],
            "rows": [
              {
                "블록": "1. 오늘 있었던 일",
                "내용": "오늘은 네가 일, 휴식, 휴대폰, 취미, 개인 과제에 시간을 더 많이 쓰고 싶었는데, 엄마는 그 때문에 관계 시간이 계속 뒤로 밀린다고 느꼈을 수 있어.",
                "출처": "td14-title / td14-say_initiator"
              },
              {
                "블록": "2. 너는 이런 마음이었을 거야",
                "내용": "너는 \"나는 해야 할 일이 많을 뿐이다\", \"잠깐 쉬는 것까지 문제 삼는 것 같다\", \"내 개인 시간은 인정받지 못한다\", \"관계를 위해 모든 시간을 내놓으라는 것처럼 들린다\"고 느꼈을 수 있어.",
                "출처": "td14-child_feelings"
              },
              {
                "블록": "3. 엄마 마음은 이랬어",
                "내용": "엄마는 네가 일부러 밀어낸다고 단정하려는 게 아니라, 반복적으로 다른 일이 먼저 오면 관계 안에서 뒤로 밀린 느낌을 받을 수 있어.",
                "출처": "td14-say_initiator"
              },
              {
                "블록": "4. 이건 네 잘못이 아니야",
                "내용": "네가 개인 시간이나 쉬는 시간이 필요하다고 해서 네가 나쁜 사람이라는 뜻은 아니야. 실제 업무 과부하, 피로, 개인 회복 시간, 디지털 활동의 즉각 보상, 취미를 통한 정서 조절이 있을 수 있어.",
                "출처": "td14-child_explain / td14-say_initiator"
              },
              {
                "블록": "5. 이렇게 해보면 어떨까",
                "내용": "다음에는 \"지금 바로 길게 이야기하기는 어렵지만, 오늘 9시에 15분은 너에게 집중해서 이야기할게\", \"'나중에'라고만 말해서 너를 기다리게 한 것 같아. 앞으로는 가능한 시간을 구체적으로 말하겠다\"라고 말해볼 수 있어.",
                "출처": "td14-say_responder"
              },
              {
                "블록": "6. 응원",
                "내용": "너는 해야 할 일도 많고, 혼자 쉬는 시간도 필요했을 수 있어. 네 개인 시간이 인정받고 싶다는 마음을 알아차린 건 균형을 찾는 단서가 될 수 있어.",
                "출처": "[출처: 대표 승인 D-6, 2026-07-09]"
              }
            ]
          }
        ]
      },
      "tier3": {
        "header": "D-구간3(11세+). 아이용 결과 리포트 [성인에 가까운 톤, 6블록]",
        "tables": [
          {
            "header": [
              "블록",
              "내용"
            ],
            "rows": [
              {
                "블록": "오늘 있었던 일",
                "내용": "네 시간, 에너지, 관심이 일·취미·휴식·디지털 활동 쪽으로 더 많이 가면서, 관계 시간이 뒤로 밀린 것처럼 느껴진 상황이었어."
              },
              {
                "블록": "너는 이런 마음이었을 거야",
                "내용": "너는 해야 할 일이 많고, 잠깐 쉬는 것까지 문제 삼는 것처럼 느꼈을 수 있어. 개인 시간이 인정받지 못하고, 관계를 위해 모든 시간을 내놓으라는 말처럼 들렸을 수도 있어."
              },
              {
                "블록": "상대방 마음은 이랬어",
                "내용": "상대방은 네가 일부러 밀어낸다고 단정하려는 게 아니라, 반복적으로 다른 일이 먼저 오면 자신이 뒤로 밀린다고 느꼈을 수 있어. 긴 시간이 아니라도, 관계가 중요하다는 구체적인 신호가 필요했을 수 있어."
              },
              {
                "블록": "이건 네 잘못이 아니야",
                "내용": "네가 쉬고 싶거나 개인 시간이 필요하다고 해서 관계를 소홀히 하는 사람이라는 뜻은 아니야. 바쁨, 피로, 회복 시간, 개인 활동이 실제로 필요했을 수 있어."
              },
              {
                "블록": "이렇게 해보면 어떨까",
                "내용": "\"내 개인 시간이 필요한 것과, 네가 소외감을 느끼지 않도록 연결 신호를 주는 것은 둘 다 중요해\"라고 말해볼 수 있어."
              },
              {
                "블록": "응원",
                "내용": "너의 시간도 중요하고, 관계 시간도 중요해. 둘 중 하나를 없애기보다, 짧아도 실제로 연결되는 시간을 정해볼 수 있어."
              }
            ]
          }
        ]
      }
    },
    "E": {
      "header": "6. E. 데일리 미션 & 효과 피드백",
      "text": "**미션**: 이번 주 관계 시간을 남는 시간으로 두지 않고, 작고 구체적인 시간으로 먼저 정해보기. 예: \"오늘 9시에 15분은 휴대폰 없이 이야기하기.\" [출처: td14-say_responder / td14-parent_coaching.coaching_steps]\n\n**효과 확인 질문** *(effect_signals 기반)*: 지난번보다 관계 시간이 계속 남는 시간으로 밀리는 구조가 줄어들었나요? [출처: td14-parent_coaching.effect_signals]\n\n**변화 질문** *(effect_signals 기반)*: \"나중에\"라는 모호한 표현으로 인한 불확실성이 줄어들었나요? 개인 회복 시간과 관계 시간이 충돌하지 않도록 분리되었나요? 취소나 변경이 있었을 때 대체 시간이 제안되었나요? [출처: td14-parent_coaching.effect_signals]\n\n**회고 질문** *(retro_question_pool 7개 원문 그대로)*: 이번 주에 관계 시간이 실제로 있었는가? 개인 회복 시간은 충분했는가? 한 사람이 계속 기다리거나 요구하는 역할을 했는가? \"나중에\"라고 말하고 지키지 못한 일이 있었는가? 취소가 있었을 때 대체 시간이 제안되었는가? 디지털 활동이나 업무가 관계 시간을 반복적으로 밀어냈는가? 다음 주에 조정할 수 있는 작은 시간은 무엇인가? [출처: td14-parent_coaching.retro_question_pool]\n\n**안 했을 때 위로**: 이 칸은 자산에 해당 내용이 없어 비워둡니다. [출처: 자산 없음]"
    },
    "F": {
      "header": "7. F. 자산 부족 칸 보완 제안 / 대표 검토 메모",
      "tables": [
        {
          "header": [
            "위치",
            "현재 상태",
            "활용 가능한 자산",
            "보완 제안",
            "주의"
          ],
          "rows": [
            {
              "위치": "B-정민님 조건부 블록",
              "현재 상태": "자산 없음",
              "활용 가능한 자산": "td14 전체 자산",
              "보완 제안": "정민님이 직접 입력하지 않은 경우 의도·역할·개입 방식을 단정하지 않고 비워두는 것이 안전",
              "주의": "정민님을 소외시키는 사람 또는 통제받는 사람으로 임의 배치하지 않기"
            },
            {
              "위치": "D-6 아이용 응원",
              "현재 상태": "자산 없음",
              "활용 가능한 자산": "td14-child_feelings / td14-child_explain",
              "보완 제안": "\"개인 시간이 필요하다는 것과 관계 신호를 주는 것은 동시에 가능함\"을 아이용 승인 문구로 만들 수 있음",
              "주의": "\"네 개인 시간을 줄여야 한다\"로 끝나면 방어가 커질 수 있음"
            },
            {
              "위치": "관계 시간 예약 카드",
              "현재 상태": "활용 가능",
              "활용 가능한 자산": "td14-say_together / td14-parent_coaching.coaching_steps",
              "보완 제안": "\"오늘 9시 15분\"처럼 작고 구체적인 관계 시간 카드로 재사용 가능",
              "주의": "관계 시간을 의무 수행처럼 만들지 않기"
            },
            {
              "위치": "'나중에' 전환 카드",
              "현재 상태": "활용 가능",
              "활용 가능한 자산": "td14-say_together / td14-translate_pairs",
              "보완 제안": "\"나중에\"를 \"오늘 몇 시\"로 바꾸는 MVP 문장 카드로 사용 가능",
              "주의": "지킬 수 없는 시간을 말하면 신뢰가 더 낮아질 수 있음"
            }
          ]
        }
      ]
    },
    "reuse_pool": {
      "header": "8. TD14 재사용 풀",
      "tables": [
        {
          "header": [
            "풀 이름",
            "재사용 문구",
            "출처"
          ],
          "rows": [
            {
              "풀 이름": "핵심 번역",
              "재사용 문구": "\"함께하기로 한 시간이 반복적으로 다른 일 뒤로 밀리면, 나는 관계 안에서 내가 우선순위가 아닌 것처럼 느껴져.\"",
              "출처": "td14-translate_pairs"
            },
            {
              "풀 이름": "엄마용 요청",
              "재사용 문구": "\"네가 일부러 나를 밀어낸다고 단정하려는 건 아니야. 하지만 반복적으로 다른 일이 먼저 오면 나는 뒤로 밀린 느낌을 받아.\"",
              "출처": "td14-say_initiator"
            },
            {
              "풀 이름": "관계 시간 요청",
              "재사용 문구": "\"내가 원하는 건 네 모든 시간을 갖겠다는 게 아니야. 우리 관계가 중요하다는 것을 알 수 있는 구체적인 시간이 필요해.\"",
              "출처": "td14-say_initiator"
            },
            {
              "풀 이름": "'나중에' 구체화",
              "재사용 문구": "\"'나중에'라는 말만 반복되면 나는 기다리는 사람으로 남는 것 같아.\"",
              "출처": "td14-say_initiator"
            },
            {
              "풀 이름": "이안이 관점",
              "재사용 문구": "\"지금 바로 길게 이야기하기는 어렵지만, 오늘 9시에 15분은 너에게 집중해서 이야기할게.\"",
              "출처": "td14-say_responder"
            },
            {
              "풀 이름": "함께 합의",
              "재사용 문구": "\"개인 시간과 관계 시간을 서로 지우지 않도록 따로 정하자.\" / \"관계 시간은 남는 시간이 아니라 미리 정한 시간으로 두자.\"",
              "출처": "td14-say_together"
            },
            {
              "풀 이름": "피할 말",
              "재사용 문구": "\"너한테 나는 항상 나중이야\", \"휴대폰이 나보다 중요하지?\", \"너는 가족보다 일이 먼저야\", \"너는 이기적이야\", \"나를 사랑하면 지금 당장 해.\"",
              "출처": "td14-avoid"
            },
            {
              "풀 이름": "감정 풀",
              "재사용 문구": "\"나는 해야 할 일이 많을 뿐이다\", \"잠깐 쉬는 것까지 문제 삼는 것 같다\", \"내 개인 시간은 인정받지 못한다.\"",
              "출처": "td14-child_feelings"
            },
            {
              "풀 이름": "가능한 설명 풀",
              "재사용 문구": "실제 업무 과부하, 번아웃 또는 피로, 개인 회복 시간 필요, 디지털 활동의 즉각 보상, 취미나 개인 활동을 통한 정서 조절, 관계 대화에 대한 회피",
              "출처": "td14-child_explain"
            },
            {
              "풀 이름": "부모 코칭 단계",
              "재사용 문구": "실제 시간 배분을 관찰 중심으로 확인한다 → 소외감의 관계적 영향을 말한다 → 관계 시간을 작고 구체적으로 예약한다 → 개인 시간과 관계 시간을 분리한다 → \"나중에\"를 구체적 시간으로 바꾼다 → 우선순위 신호를 정한다 → 취소나 변경이 필요할 때 대체 시간을 함께 제안한다 → 관계 시간과 개인 시간이 모두 지켜졌는지 회고한다 → 반복 실패가 있으면 구조를 다시 설계한다 → 방임, 통제, 의무 회피 가능성을 구분한다",
              "출처": "td14-parent_coaching.coaching_steps"
            }
          ]
        }
      ]
    }
  }
}
